delicious_nbdev/Sandwich.py
delicious_nbdev/__init__.py
delicious_nbdev/_modidx.py
delicious_nbdev-0.0.1.dist-info/LICENSE
delicious_nbdev-0.0.1.dist-info/METADATA
delicious_nbdev-0.0.1.dist-info/WHEEL
delicious_nbdev-0.0.1.dist-info/entry_points.txt
delicious_nbdev-0.0.1.dist-info/top_level.txt
delicious_nbdev-0.0.1.dist-info/RECORD
